cactus/__init__.py
cactus/api.py
cactus/cactus.py
cactus/changelog.py
cactus/constants.py
cactus/git_utils.py
cactus/grouper.py
cactus/prompt.py
cactus/utils.py
cactus_commit-4.7.0.dist-info/licenses/LICENSE
cactus_commit-4.7.0.dist-info/METADATA
cactus_commit-4.7.0.dist-info/WHEEL
cactus_commit-4.7.0.dist-info/entry_points.txt
cactus_commit-4.7.0.dist-info/top_level.txt
cactus_commit-4.7.0.dist-info/RECORD
