Metadata-Version: 2.4
Name: cactus-commit
Version: 4.7.0
Summary: A tool for streamlined commit messaging using AI
Home-page: https://github.com/esauvisky/cactus
Author: @emi
Author-email: esauvisky@gmail.com
Classifier: Programming Language :: Python :: 3
Classifier: License :: OSI Approved :: MIT License
Classifier: Operating System :: OS Independent
Requires-Python: >=3.10
License-File: LICENSE
Requires-Dist: numpy
Requires-Dist: scikit-learn
Requires-Dist: thefuzz
Requires-Dist: unidiff
Requires-Dist: openai
Requires-Dist: google-generativeai
Requires-Dist: tiktoken
Requires-Dist: loguru
Requires-Dist: inquirer>=3.4.0
Requires-Dist: prompt_toolkit>=3.0.48
Dynamic: author
Dynamic: author-email
Dynamic: classifier
Dynamic: description
Dynamic: description-content-type
Dynamic: home-page
Dynamic: license-file
Dynamic: requires-dist
Dynamic: requires-python
Dynamic: summary
